cli.py
hugo_sizer-0.2.1.dist-info/LICENSE
hugo_sizer-0.2.1.dist-info/METADATA
hugo_sizer-0.2.1.dist-info/WHEEL
hugo_sizer-0.2.1.dist-info/entry_points.txt
hugo_sizer-0.2.1.dist-info/top_level.txt
hugo_sizer-0.2.1.dist-info/RECORD
